{
  "gp_data": {
    "summary": {
      "RRMSE": {
        "mean": 0.3188533751693593,
        "std": 0.048529563484011926,
        "median": 0.3191750130346687,
        "min": 0.23359645436933762,
        "max": 0.45910686586042226,
        "count": 20
      },
      "NIS": {
        "mean": 2.7301255096714234,
        "std": 0.7193352793111762,
        "median": 2.6078844624678252,
        "min": 1.6525513612728,
        "max": 3.740870917558326,
        "count": 20
      },
      "Time": {
        "mean": 0.32746210098266604,
        "std": 0.03316221114170346,
        "median": 0.31767940521240234,
        "min": 0.30114269256591797,
        "max": 0.4526979923248291,
        "count": 20
      }
    },
    "metrics": [
      {
        "Time": 0.4526979923248291,
        "RRMSE": 0.3321472772323624,
        "RMSE": 13.787311077270967,
        "MSE": 190.08994674143872,
        "NIS": 3.347603057066245
      },
      {
        "Time": 0.3447706699371338,
        "RRMSE": 0.31942090357495134,
        "RMSE": 12.587077624089387,
        "MSE": 158.43452311485174,
        "NIS": 2.412782569192926
      },
      {
        "Time": 0.3206007480621338,
        "RRMSE": 0.3463249776342018,
        "RMSE": 13.978745617459829,
        "MSE": 195.40532903765236,
        "NIS": 3.7002139226524102
      },
      {
        "Time": 0.34146642684936523,
        "RRMSE": 0.31920891840241267,
        "RMSE": 13.78258571013222,
        "MSE": 189.9596688571409,
        "NIS": 3.684751988181745
      },
      {
        "Time": 0.33238911628723145,
        "RRMSE": 0.3065195799865019,
        "RMSE": 11.167413180741063,
        "MSE": 124.71111714938921,
        "NIS": 2.375156724863477
      },
      {
        "Time": 0.36144185066223145,
        "RRMSE": 0.31524349080510244,
        "RMSE": 11.908650458531497,
        "MSE": 141.81595574348242,
        "NIS": 3.065208692147764
      },
      {
        "Time": 0.3090250492095947,
        "RRMSE": 0.3932679437574606,
        "RMSE": 15.056834572222353,
        "MSE": 226.70826733527028,
        "NIS": 3.6368997206538136
      },
      {
        "Time": 0.31171536445617676,
        "RRMSE": 0.26689125198210384,
        "RMSE": 10.657029295466996,
        "MSE": 113.57227340444177,
        "NIS": 1.6714944772167886
      },
      {
        "Time": 0.30114269256591797,
        "RRMSE": 0.3315163369779099,
        "RMSE": 12.765751510759559,
        "MSE": 162.96441163445996,
        "NIS": 3.031466051571773
      },
      {
        "Time": 0.3147580623626709,
        "RRMSE": 0.3158103078538028,
        "RMSE": 11.89856234348462,
        "MSE": 141.57578584179024,
        "NIS": 2.261467648108316
      },
      {
        "Time": 0.3217935562133789,
        "RRMSE": 0.2573869007413655,
        "RMSE": 10.261867534393087,
        "MSE": 105.30592529343085,
        "NIS": 1.881028798400769
      },
      {
        "Time": 0.32340455055236816,
        "RRMSE": 0.28474319415220817,
        "RMSE": 10.931201938425396,
        "MSE": 119.49117581863514,
        "NIS": 2.0619380437810575
      },
      {
        "Time": 0.32422351837158203,
        "RRMSE": 0.30483738467762017,
        "RMSE": 12.118326855307247,
        "MSE": 146.85384577206082,
        "NIS": 2.443599803455089
      },
      {
        "Time": 0.3125913143157959,
        "RRMSE": 0.3242260124212202,
        "RMSE": 13.320796724786879,
        "MSE": 177.44362538309286,
        "NIS": 2.910981981598504
      },
      {
        "Time": 0.3116343021392822,
        "RRMSE": 0.2704263739428924,
        "RMSE": 10.767411281742072,
        "MSE": 115.93714571018647,
        "NIS": 2.146635891613772
      },
      {
        "Time": 0.33165645599365234,
        "RRMSE": 0.45910686586042226,
        "RMSE": 15.924174978297302,
        "MSE": 253.57934873942986,
        "NIS": 3.740870917558326
      },
      {
        "Time": 0.31024789810180664,
        "RRMSE": 0.33649031806975804,
        "RMSE": 13.21883131482469,
        "MSE": 174.73750132978986,
        "NIS": 2.772169121480561
      },
      {
        "Time": 0.3065025806427002,
        "RRMSE": 0.3191411076669248,
        "RMSE": 12.37904160964523,
        "MSE": 153.24067117332794,
        "NIS": 2.1483665539813797
      },
      {
        "Time": 0.31363606452941895,
        "RRMSE": 0.23359645436933762,
        "RMSE": 8.993979959888398,
        "MSE": 80.89167551887411,
        "NIS": 1.6525513612728
      },
      {
        "Time": 0.3035438060760498,
        "RRMSE": 0.3407619032786276,
        "RMSE": 13.061376813098429,
        "MSE": 170.59956425374526,
        "NIS": 3.657322868630957
      }
    ],
    "gp_model_info": {
      "model_str": "GPR(\n  (likelihood): GaussianLikelihood(\n    (noise_covar): HomoskedasticNoise(\n      (raw_noise_constraint): GreaterThan(1.000E-04)\n    )\n  )\n  (mean_module): ConstantMean()\n  (covar_module): CombinedKernel(\n    (cat_kernel): GaussianKernel(\n      (raw_lengthscale_constraint): SoftClamp(-6.0, 3.0, margin=0.009999999776482582)\n    )\n    (cat_encoder_0): MatrixEncoder()\n    (cat_encoder_1): MatrixEncoder()\n    (cat_encoder_2): MatrixEncoder()\n  )\n)",
      "cont_cols": [],
      "cat_cols": [
        [
          0,
          1,
          2,
          3,
          4,
          5,
          6,
          7,
          8,
          9
        ],
        [
          10,
          11,
          12,
          13,
          14,
          15,
          16,
          17,
          18,
          19,
          20,
          21
        ],
        [
          22,
          23
        ]
      ],
      "source_cols": [],
      "qual_dict": {
        "0": 10,
        "1": 12,
        "2": 2
      },
      "input_dim": 24,
      "train_samples": 133,
      "test_samples": 90,
      "y_train_mean": 165.46616541353384,
      "y_train_std": 37.8956999383956,
      "dtype": "torch.float64",
      "device": "cpu",
      "num_epochs": 10,
      "num_runs": 16,
      "lr": 0.1,
      "optimizer": "Adam",
      "convergence_patience": 10,
      "initializer": null
    }
  },
  "tabpfn_data": {
    "summary": {
      "RRMSE": {
        "mean": 0.3282116610804635,
        "std": 0.034197556804397185,
        "median": 0.33158254614519067,
        "min": 0.2532281112021332,
        "max": 0.3998376852375706,
        "count": 20
      },
      "NIS": {
        "mean": 8.983371254132031,
        "std": 1.0557342248426325,
        "median": 8.879544355162025,
        "min": 6.910432372980887,
        "max": 11.770787281735728,
        "count": 20
      },
      "Time": {
        "mean": 0.08951084613800049,
        "std": 0.017415584931785872,
        "median": 0.09296083450317383,
        "min": 0.06254363059997559,
        "max": 0.11557888984680176,
        "count": 20
      }
    },
    "metrics": [
      {
        "Time": 0.1040811538696289,
        "RRMSE": 0.32837536193749,
        "RMSE": 13.630740263381258,
        "MSE": 185.79708012776294,
        "NIS": 8.783851792001395
      },
      {
        "Time": 0.06865167617797852,
        "RRMSE": 0.32098141395720065,
        "RMSE": 12.648570986279317,
        "MSE": 159.98634799494693,
        "NIS": 8.75061385283526
      },
      {
        "Time": 0.0736382007598877,
        "RRMSE": 0.33721675937779266,
        "RMSE": 13.611109800648698,
        "MSE": 185.26231000531504,
        "NIS": 9.09820861922944
      },
      {
        "Time": 0.0751500129699707,
        "RRMSE": 0.35862931761997136,
        "RMSE": 15.484652913212988,
        "MSE": 239.7744758426755,
        "NIS": 9.751894122224895
      },
      {
        "Time": 0.0843346118927002,
        "RRMSE": 0.32975947752073137,
        "RMSE": 12.014111254822511,
        "MSE": 144.33886924325296,
        "NIS": 9.375455417065224
      },
      {
        "Time": 0.11471295356750488,
        "RRMSE": 0.34513435972467205,
        "RMSE": 13.037809093832257,
        "MSE": 169.9844659672151,
        "NIS": 9.919846527885884
      },
      {
        "Time": 0.06254363059997559,
        "RRMSE": 0.37713326557433047,
        "RMSE": 14.439094977282823,
        "MSE": 208.48746376299403,
        "NIS": 9.332207491181089
      },
      {
        "Time": 0.10042905807495117,
        "RRMSE": 0.28313654209413835,
        "RMSE": 11.30570747937735,
        "MSE": 127.81902160924898,
        "NIS": 7.3868740896180975
      },
      {
        "Time": 0.09314179420471191,
        "RRMSE": 0.3494147712042298,
        "RMSE": 13.454969320800995,
        "MSE": 181.036199423696,
        "NIS": 9.521540846720635
      },
      {
        "Time": 0.07824015617370605,
        "RRMSE": 0.3017076402578351,
        "RMSE": 11.36722607792567,
        "MSE": 129.2138287066734,
        "NIS": 8.315408738758414
      },
      {
        "Time": 0.06898760795593262,
        "RRMSE": 0.3019095272433199,
        "RMSE": 12.036959017799287,
        "MSE": 144.88838239617957,
        "NIS": 8.23781140587063
      },
      {
        "Time": 0.07087969779968262,
        "RRMSE": 0.29228440986036486,
        "RMSE": 11.220706844811398,
        "MSE": 125.90426209719735,
        "NIS": 8.256616958747628
      },
      {
        "Time": 0.06906604766845703,
        "RRMSE": 0.30782241027238966,
        "RMSE": 12.236991814551436,
        "MSE": 149.74396866939884,
        "NIS": 8.49673264819616
      },
      {
        "Time": 0.10471987724304199,
        "RRMSE": 0.30023906355130964,
        "RMSE": 12.335295075619936,
        "MSE": 152.15950460261342,
        "NIS": 8.285574734758315
      },
      {
        "Time": 0.09942507743835449,
        "RRMSE": 0.33780744223546527,
        "RMSE": 13.45028449536766,
        "MSE": 180.91015300632765,
        "NIS": 9.301881908789921
      },
      {
        "Time": 0.11557888984680176,
        "RRMSE": 0.35178874898132784,
        "RMSE": 12.201833626853395,
        "MSE": 148.88474385741026,
        "NIS": 8.910252173818332
      },
      {
        "Time": 0.11309957504272461,
        "RRMSE": 0.3334056147696499,
        "RMSE": 13.097650495078314,
        "MSE": 171.5484484912252,
        "NIS": 8.848836536505717
      },
      {
        "Time": 0.10259175300598145,
        "RRMSE": 0.3544212989873474,
        "RMSE": 13.747511373833552,
        "MSE": 188.99406897368286,
        "NIS": 10.41259756371695
      },
      {
        "Time": 0.09816527366638184,
        "RRMSE": 0.2532281112021332,
        "RMSE": 9.749842152275962,
        "MSE": 95.05942199429717,
        "NIS": 6.910432372980887
      },
      {
        "Time": 0.09277987480163574,
        "RRMSE": 0.3998376852375706,
        "RMSE": 15.325746865237972,
        "MSE": 234.87851697735152,
        "NIS": 11.770787281735728
      }
    ],
    "pfn_model_info": {
      "model_path": "auto",
      "fit_mode": "fit_preprocessors",
      "device": "cuda",
      "inference_precision": "auto",
      "random_state": null,
      "use_autocast": true,
      "forced_inference_dtype": null,
      "train_samples": 133,
      "test_samples": 90
    }
  }
}